{"category": "ham", "to_address": "\"Speakup is a screen review system for Linux.\" <Speakup@braille.uwo.ca>", "from_address": "\"Michael Weaver\" <weavermicha@googlemail.com>", "subject": "speakup in ubuntu", "body": "I seem to have Speakup in Ubuntu running but it does seem to take a\nlot of work as I have to switch consoles after quitting Orca, type my\nusername and password after changing to a text console, typing sudo\nmodprobe speakup_sftsyn and having to reconfirm my passwrord again\nbefore I get speech.\nIs there a quicker way?\nAlso I have noticed the speech is very low in Speakup compared with\nOrca even though they both use the same software synth.\nHow do I adjust the level?\nI tried Caps Lock 2 as I am using a laptop but although the volume\nsays 9 for my setting, the speech is still quiet.\n\n_______________________________________________\nSpeakup mailing list\nSpeakup@braille.uwo.ca\nhttp://speech.braille.uwo.ca/mailman/listinfo/speakup\n\n"}