{"category": "ham", "to_address": "beginners@perl.org, perl-beginners@moderators.isc.org", "from_address": "jeevs <jeevan.ingale@gmail.com>", "subject": "Re: Accessing hash", "body": "On May 28, 11:35 am, jeevan.ing...@gmail.com (Jeevs) wrote:\n> @hashi = @hash{qw (jeevan, sarika)};\n> print @hashi;\n>\n> this gives me the values of keys jeevan and sarika.. how does this\n> work ...\n\n\nok i got it ...\nand\nI think i was not clear in my query...\nI was expecting an hash slice to be\n%hash{qw(jeevan sarika)} which seems more logical as i said earlier...\n\n\nWEll i was browsing for more information and found out it has been\ntaken care of in perl6 :)\n\nwhere a new operator (qoute word) is introduced <> instead of qw() in\nperl5.\nu can write the above hash as\n\n@hashi = %hash;\nprint @hashi;\n\nand u can get the same output as above...\n\n\n\n-- \nTo unsubscribe, e-mail: beginners-unsubscribe@perl.org\nFor additional commands, e-mail: beginners-help@perl.org\nhttp://learn.perl.org/\n\n\n"}