{"category": "ham", "to_address": "r-help@stat.math.ethz.ch", "from_address": "Anup Nandialath <anup_nandialath@yahoo.com>", "subject": "[R] Help with optim", "body": "Dear Friends,\n\nI'm using the optim command to maximize a likelihood function. My optim command is as follows\n\nestim.out <- optim(beta, loglike, X=Xmain, Y=Y, hessian=T, method=\"BFGS\", control=c(fnscale=-1, trace=1, REPORT=1))\n\nSetting the report=1, gives me the likelihood function value (if i'm correct) at each step. The output from running this is as follows\n\ninitial  value 3501.558347 \niter   2 value 3247.277071\niter   3 value 3180.679307\niter   4 value 3157.201356\niter   5 value 3156.579887\niter   6 value 3017.715292\niter   7 value 2993.349538\niter   8 value 2987.181782\niter   9 value 2986.672719\niter  10 value 2986.658620\niter  11 value 2986.658266\niter  12 value 2986.658219\niter  13 value 2986.658156\niter  13 value 2986.658156\niter  13 value 2986.658135\nfinal  value 2986.658135 \nconverged\n\nI just wanted to know if there was any way I could get the value of each iteration into an object. At present it is dumped on the screen. But is there a way to get hold of these values through an object??\n\nThanks in advance\n\nsincerely\n\nAnup\n\n\n\n\n \n---------------------------------\nThe fish are biting.\n\n\t[[alternative HTML version deleted]]\n\n______________________________________________\nR-help@stat.math.ethz.ch mailing list\nhttps://stat.ethz.ch/mailman/listinfo/r-help\nPLEASE do read the posting guide http://www.R-project.org/posting-guide.html\nand provide commented, minimal, self-contained, reproducible code.\n\n"}