{"category": "spam", "to_address": "cruiseca@flax9.uwaterloo.ca", "from_address": "\"DVD Copying Software\" <return@anythingrading.com>", "subject": "Own the Software Hollywood Hates - Copies Everything - Final Sale", "body": "Own \nthe Software Hollywood Hates \nCopies Everything - Final Sale \nLimited \n  quantity available and then they\\u2019re gone forever\n * The #1 DVD Backup Program \n  * Create Perfect Quality Movie Backups on DVD \n* Burns DVD movies to DVD-R(W) and DVD+R(W) Discs \n  * Limited Quantity Available at a Liquidation Price \nGet \n  it now while its still legal\nNever worry about your kids trashing your DVD's again\n \n\n\n\n\n\n\n------------------------------------\nTo \n  stop receiving announcements\nPriceSavers.com\n  2445 Nevada Ave N\n  Golden Valley, MN 55427\n\n\n______________________________________________________\n\n\n\n"}