{"category": "ham", "to_address": "R-help@stat.math.ethz.ch", "from_address": "jessica.gervais@tudor.lu", "subject": "[R] spgrass6 and aggregation", "body": "\nDear all,\n\n\nI am exporting grass map into R thanks to the very useful spgrass6 package.\n\nlibrary(spgrass6)\n\n# I have 3 map I am working with a MASK map of a specific area.\n\n# 1) a landuse map\nlanduse<-readRAST6(\"landuse_mapname_in_grass\")\n\n# 2) a catchment map which divide the area in several catchements\ncatchment<-readRAST6(\"catchement_mapname_in_grass\")\n\n# 3) a precipitation map\nprecipitation<-readRAST6(\"precipitation_mapname_in_grass\")\n\n\n# then I would like to sum the precipitation spatialy over each catchment\nand landuse. So, first I cbind all maps with cbind\n\nMAP<-cbind(Dear all,\n\n______________________________________________\nR-help@stat.math.ethz.ch mailing list\nhttps://stat.ethz.ch/mailman/listinfo/r-help\nPLEASE do read the posting guide http://www.R-project.org/posting-guide.html\nand provide commented, minimal, self-contained, reproducible code.\n\n"}