{"category": "spam", "to_address": "<aeehassa@plg.uwaterloo.ca>", "from_address": "\"Bonny Jeanett\" <tmml04zokuv@laposte.net>", "subject": "World Popular Medications from A-Z, start  from $1.50 per D0SE bl", "body": "\n\nscience build fancy sugar circumstances. commit not slow drew with,\nExpress Drug MartWe are the best price on \nall high quality meds. Established by a reputable Canadian \nDoctor and Scientist, Express Drugmart's mission is to provide you with a secure online environment \nto \npurchase the safest, quality medication\nViagraa (Brand & Generic available) - as \nLOW as \n$ 2.25 per D0SECialiss (Brand & Generic available) - \nas \nLOW as $ 2.25 per D0SE\nValiumm - as LOW as $ 1.50 \nper D0SEXanaxxxxx - only $ 1.50 \nper D0SEAmbienn - only \n$ 1.65 per D0SE\nAtivann - only $ 1.50 per D0SESomaa - only $ 1.50 per D0SE\n\nClenbuterol - only $ 2.50 per D0SE\nMeridiaa (brand name) - only $ 3.99 per D0SE\n\nSee What Meds Has Special DiscountClick On This Link\n\n\nneed raised whom circumstances. surprise filled account?\n\n\n"}