{"category": "ham", "to_address": "\"Tavpritesh Sethi\" <tavpritesh@gmail.com>", "from_address": "Petr PIKAL <petr.pikal@precheza.cz>", "subject": "[R] Odp:  how to iterate", "body": "Hi\n\nas you did not specify your code (which you said it had failed) I try to \ngive you a suggestion how I would do such tasks.\n\nfor (i in 1:100)  {\n\nsample(something, no, replace =TRUE)\nresult <-perform a test\nstore.a result[i] <- result\n\n}\n\nRegards\nPetr\n\n\nr-help-bounces@stat.math.ethz.ch napsal dne 26.06.2007 16:08:16:\n\n> for the following example dataset:-\n>    Category Variable 1 127 1 261 1 142 1 183 1 234 1 162 2 173 2 321 2 \n168 2\n> 197 2 213 2 261 3 198 3 126 3 167 3 154 3 134 3 187 3 109 3 210\n> I have performed Anova on the measured variable (column#2) for the \ngroups\n> 1,2&3 (column#1). Now I want to randomize the values in C#2 and \nreperform\n> the test, say, a hundred times. Please suggest a way for this iteration. \nThe\n> loop I tried to write didn't work.\n> Thanks.\n> \n>    [[alternative HTML version deleted]]\n> \n> ______________________________________________\n> R-help@stat.math.ethz.ch mailing list\n> https://stat.ethz.ch/mailman/listinfo/r-help\n> PLEASE do read the posting guide \nhttp://www.R-project.org/posting-guide.html\n> and provide commented, minimal, self-contained, reproducible code.\n\n______________________________________________\nR-help@stat.math.ethz.ch mailing list\nhttps://stat.ethz.ch/mailman/listinfo/r-help\nPLEASE do read the posting guide http://www.R-project.org/posting-guide.html\nand provide commented, minimal, self-contained, reproducible code.\n\n"}