{"category": "ham", "to_address": "\"Speakup is a screen review system for Linux.\" <speakup@braille.uwo.ca>", "from_address": "\"Littlefield, Tyler\" <compgeek13@gmail.com>", "subject": "frozen messages in mailq, think they're clogging smtp", "body": "Hello list,\nI've got a question.\nWhen I type mailq, I've got a bunch of frozen messages.\nIs there a way to clear this?\nThanks,\n_______________________________________________\nSpeakup mailing list\nSpeakup@braille.uwo.ca\nhttp://speech.braille.uwo.ca/mailman/listinfo/speakup\n\n"}