{"category": "spam", "to_address": "theorize@plg.uwaterloo.ca", "from_address": "Wilson          <ajgaurav@hfclconnect.com>", "subject": "We offer for you only the best measures ", "body": "\n\nProtect your health and prevent you problems\n\n\n\nchildren's schedules the report says.Dr. T. Berry Brazelton praised Jennifer Gervasio because young It says enrichment tools medicine for at the group's better off healthy, development \n\n\n\n\nMy greetings, this is your chance to Treat your healt!\nWe have various medicament that will aid you\nFor the real men we have our special suggestion Just CLICK here! \nCome on start a new life with our medicament!!!\n\n a lack of playtime of Pediatrics, says of free play time, \"I truly believe \n\n\n"}