{"category": "ham", "to_address": "Robert Dunne <rob.dunne@gmail.com>, r-help@stat.math.ethz.ch", "from_address": "Dirk Eddelbuettel <edd@debian.org>", "subject": "Re: [R] compiler cannot create executables", "body": "On Wed, Jun 20, 2007 at 09:10:47AM -0500, Dirk Eddelbuettel wrote:\n> On Wed, Jun 20, 2007 at 10:25:07PM +1000, Robert Dunne wrote:\n> > Hi List,\n> > \n> > \n> > I get an error message \"compiler cannot create executables\" when I try \n> > to install a package.\n> > \n> > Searching the list archives reveals many messages with the same error \n> > message. The advice is generally to install g++ and development libraries.\n> > \n> > However, I have g++ installed and can compile and run programs as myself \n> > and via sudo. I got the library to install by using\n> > \n> > %sudo R CMD INSTALL --no-configure e1071_1.5-16.tar.gz\n> \n> This statement of your conflicts with the msg you show below. Do you,\n> or don't you, succeed?\n> \n> > can anyone explain this? Also where is the config.log that I should look \n> > in (see output below)? Isn't that in a tmp directory that is removed \n> > when the install fails?\n> > \n> > \n> > %  sudo R CMD INSTALL e1071_1.5-16.tar.gz\n> > Password:\n> > * Installing *source* package 'e1071' ...\n> > checking for C++ compiler default output file name... configure: error: \n> > C++ compiler cannot create executables\n> > See `config.log' for more details.\n> > \n> > R 2.3.1 on kubuntu  breezy (5.10 I think)\n> \n> Please try \n> \n>        $ sudo apt-get install r-base-dev\n> \n> as you seem to missing g++, and probably a host of other things.\n\nI don't have access to a 'breezy' box anymore but what it could be is\nthat R expects a different compiler version then the system has as\ndefault -- g++-4.0 vs g++-3.4.\n\nWhat does 'grep g++ /etc/R/Makeconf' yield?\n\n-- \nHell, there are no rules here - we're trying to accomplish something. \n                                                  -- Thomas A. Edison\n\n______________________________________________\nR-help@stat.math.ethz.ch mailing list\nhttps://stat.ethz.ch/mailman/listinfo/r-help\nPLEASE do read the posting guide http://www.R-project.org/posting-guide.html\nand provide commented, minimal, self-contained, reproducible code.\n\n"}