{"category": "ham", "to_address": "\"Gerald (Jerry) Carter\" <jerry@samba.org>", "from_address": "Jeremy Allison <jra@samba.org>", "subject": "Re: [Samba] Re: Win32 services management?", "body": "On Mon, Apr 16, 2007 at 11:58:01AM -0500, Gerald (Jerry) Carter wrote:\n> -----BEGIN PGP SIGNED MESSAGE-----\n> Hash: SHA1\n> \n> Jeremy Allison wrote:\n> > On Mon, Apr 16, 2007 at 05:50:35PM +0300, Danny Tylman wrote:\n> >> Hi,\n> >>\n> >> Attached is a bzr-diff containing the changes made in order to remotely\n> >> create/delete service.\n> > \n> > This looks really nice work - thanks ! I'll evaluate it and\n> > if all looks ok it'll get in for 3.0.26.\n> \n> Jeremy,  if you don't mind I'd like to have final sign off\n> on this one since teh svcctl code is near and dear to my heart. :-)\n\nNo problem. All yours :-).\n\n"}