{"category": "ham", "to_address": "Prof Brian Ripley <ripley@stats.ox.ac.uk>", "from_address": "Martin Maechler <maechler@stat.math.ethz.ch>", "subject": "Re: [R] data encapsulation with classes", "body": ">>>>> \"BDR\" == Prof Brian Ripley \n>>>>>     on Mon, 9 Apr 2007 08:24:32 +0100 (BST) writes:\n\n    BDR> On Sun, 8 Apr 2007, hadley wickham wrote:\n    >> On 4/8/07, Roger Bivand  wrote:\n    >>> On Sun, 8 Apr 2007, Peter Williams wrote:\n\n     >>>> Hi All,\n     >>>> \n     >>>> I'm new to R from a C and Octave/Matlab background.  I\n     >>>> am trying to construct some classes in R to which I\n     >>>> want to attach pieces of data.  First, is attr(obj,\n     >>>> 'member name') <- data the accepted way of doing this?\n\n    >>>  No, it isn't. You seem to be trying to deduce new-style\n    >>> classes from a representation used before R 2.4,\n\n    BDR> (actually, still used)\n\n    >>> but in any case it would not be sensible. Please consult\n    >>> John M. Chambers. Programming with Data.  Springer, New\n    >>> York, 1998, and/or William N. Venables and Brian\n    >>> D. Ripley.  S Programming. Springer, New York, 2000, or\n    >>> for a shorter online resource:\n    >>> \n    >>> http://www.stat.auckland.ac.nz/S-Workshop/Gentleman/Methods.pdf\n\n    >>  Unfortunately, all of those references are at least 4\n    >> years out of date when it comes to S4 methods.  Is there\n    >> any comprehensive reference of the current implementation\n    >> of the S4 OO system apart from the source code?\n\n?Methods {i.e. help(Methods)} is not about the *implementation*\nbut still explains quite a bit about the method dispatch part of\nS4.  It has had a URL to for the \"How S4 Methods Work\" technical\nreport by John Chambers; I've now also added a link to that from\nhttp://developer.R-project.org/ (will only be active in ~ a day).\n\nMartin\n\n    BDR> Not that I know of, and it is a moving target.  (E.g. I\n    BDR> asked recently about some anomalies in the S4 bit\n    BDR> introduced for 2.4.0 and what the intended semantics\n    BDR> are.)  I've said before that I believe we can only help\n    BDR> solve some of the efficiency issues with S4 if we have\n    BDR> a technical manual.\n\n    BDR> It is unfair to pick out S4 here, but the 'R Internals'\n    BDR> manual is an attempt to document important\n    BDR> implementation details (mainly by studying the code),\n    BDR> and that has only got most of the way through\n    BDR> src/main/*.c.\n\n    BDR> -- Brian D. Ripley, ripley@stats.ox.ac.uk Professor of\n    BDR> Applied Statistics, http://www.stats.ox.ac.uk/~ripley/\n    BDR> University of Oxford, Tel: +44 1865 272861 (self) 1\n    BDR> South Parks Road, +44 1865 272866 (PA) Oxford OX1 3TG,\n    BDR> UK Fax: +44 1865 272595\n\n______________________________________________\nR-help@stat.math.ethz.ch mailing list\nhttps://stat.ethz.ch/mailman/listinfo/r-help\nPLEASE do read the posting guide http://www.R-project.org/posting-guide.html\nand provide commented, minimal, self-contained, reproducible code.\n\n"}