{"category": "ham", "to_address": "jda_vies_tx@tx.rr.com, debian-desktop@lists.debian.org,\n   debian-publicity@lists.debian.org", "from_address": "\"Andrew Donnellan\" <ajdlinux@gmail.com>", "subject": "Re: congratulations to all Debian contributors", "body": "On 4/16/07, Luis Matos  wrote:\n> just a point ...\n>\n> from the reviews i read i found that all of them had the same\n> supposition: debian is only the main repository.\n\nThat's because Debian *is* only the main repository. contrib and\nnon-free are part of the Debian *project* (so they use project\ninfrastructure and mirrors and so on), but not part of the official\nDebian distribution.\n\n-- \nAndrew Donnellan\najdlinuxATgmailDOTcom (primary)    ajdlinuxATexemailDOTcomDOTau (secure)\nhttp://andrewdonnellan.com         http://ajdlinux.wordpress.com\najdlinux@jabber.org.au             hkp://subkeys.pgp.net 0x5D4C0C58\n            http://linux.org.au    http://debian.org\n        Get free rewards - http://ezyrewards.com/?id=23484\n        Spammers only === ajdspambucket@exemail.com.au ===\n\n\n-- \nTo UNSUBSCRIBE, email to debian-desktop-REQUEST@lists.debian.org\nwith a subject of \"unsubscribe\". Trouble? Contact listmaster@lists.debian.org\n\n"}