{"category": "ham", "to_address": "<Volker.Lendecke@SerNet.DE>", "from_address": "\"McCall, Don (GSE-WTEC-Alpharetta)\" <don.mccall@hp.com>", "subject": "RE: Patch for Invalid loader fixup error on gwen (hp-ux 11.11) in\n\tthe build farm...", "body": "Thanks, Volker! \n\n-On Thu, May 17, 2007 at 09:32:07PM -0400, McCall, Don\n(GSE-WTEC-Alpharetta) wrote:\n> The attached patch to configure.in modifies the PICFLAG for HP-UX IA32\n\nThere's HP/UX on IA32??? Does it run on VMWare? ;-))\n\n>>>that's what I get for trying to write intelligently after 9:00pm ;-)\n\n\n"}