{"category": "spam", "to_address": "mail@flax9.uwaterloo.ca", "from_address": "Timothy Leary <kdlfeipybksv@brainerdoil.com>", "subject": "All spectrum of digital technique", "body": "\n\n\n\n\n\n\n\n\n\n\nWe represent for you  internet shop of digital technique and accessories! \nWe have the lowest prices in spite of that!\nGo to purchase \nSnatch from price list:\n\nName of goodsPrice in other shopsOur Price\nCanon EOS 1D$3,499.95$2,656.70Apple iPod Video 80GB White$338.31$218.07Apple 15.4\" MacBook Pro$2,299.00$1,784.35Canon EOS 5D Digital SLR Camera $2,649.00$1,782.38Apple iPod Digital player - HD 30 GB - AAC$244.99$176.00Apple 13.3\" MacBook$1,401.98$793.03Apple iPod Digital player - HD 30 GB - AAC$244.99$176.00Sony Playstation 3 Premium $790.00$416.35\nGuarantee for year and more!\n\nI don't sign my son up Noted pediatrician and author \"I hope it will have some effect,\"would worry if \n\n\n\n"}