{"category": "spam", "to_address": "producttestpanel@flax9.uwaterloo.ca", "from_address": "InsuriDailyLane <InsuriDailyLane@dailylanedepot.com>", "subject": "Are You Paying Too Much For Health Insurance", "body": "\n\n251839499// Netcong  is a Borough in Morris County, New Jersey, United States. As of the/United S\n\nYou have been selected to receive a free personalized health\ninsurance quote by Real Health Coverage.\n\nMedical Plans. Dental Plans. Prescription Plans. And Much More.\nClick Here\n\nAffordable programs are available for all ages and conditions.\n\nYou can afford health insurance. Don't get caught without it.\n\nClick here now to find out more!!!\nClick Here\n\n\n\n\n\n\n\n\n\n\n"}