{"category": "spam", "to_address": "catchall@speedy.uwaterloo.ca", "from_address": "\"bigdito Lachance\" <Lachancevsvgw@addaxcomputing.com>", "subject": "And to judge from the quality of his equipment - which is very expensive - he's been at it for a while.", "body": "\n\n\n\n\n\n\n\nThe last thing I want is Moiraine meddling. See if \nthe command line is empty.\nAttribute grammars permit the explicit description \nof the environment and its interaction with the body of the program. This readme \nfile describes the installation procedures for all Sentinel System Drivers.\nYou'll know where to stand them. This is EE v5.\nBy default, the last 1000 records of the log file \nis displayed initially.\nThen I wonder what these people would do to fill \ntheir already-from my viewpoint--empty lives, and I resolve to stop wondering.\nShivering, he forced it to silence.\n\u00a0\n\u00a0\n"}