{"category": "ham", "to_address": "\"'Jenny Barnes'\" <jmb@mssl.ucl.ac.uk>, <r-help@stat.math.ethz.ch>", "from_address": "\"Daniel Nordlund\" <res90sx5@verizon.net>", "subject": "Re: [R] random numbers selection - simple example", "body": "> -----Original Message-----\n> From: r-help-bounces@stat.math.ethz.ch [mailto:r-help-bounces@stat.math.ethz.ch]\n> On Behalf Of Jenny Barnes\n> Sent: Wednesday, June 06, 2007 7:55 AM\n> To: r-help@stat.math.ethz.ch\n> Subject: Re: [R] random numbers selection - simple example\n> \n> You're all stars - thanks for the replies - I will go ahead and use\n> sample...........\n> I need to do this about 10,000 times - any suggestions for this or simply put it\n> in a loop 10,000 times outputting each time to an array?\n> \n> Best Wishes,\n> \n> Jenny\n> \n> \n> >\n> >\n> >  use sample(c(0:42), 15, replace=T)\n> >\n> >hope it helps,\n> >kevin\n\nYou could try something like the following\n\ns<-matrix(sample(c(0:42), 10000*15, replace=TRUE), 10000, 15)\n\nwhich will give you a 10000 row matrix with 1 sample of size 15 per row.\n\nHope this is helpful,\n\nDan\n\nDaniel Nordlund\nBothell, WA USA\n\n______________________________________________\nR-help@stat.math.ethz.ch mailing list\nhttps://stat.ethz.ch/mailman/listinfo/r-help\nPLEASE do read the posting guide http://www.R-project.org/posting-guide.html\nand provide commented, minimal, self-contained, reproducible code.\n\n"}